whitechapel/VERSION
whitechapel/__init__.py
whitechapel/__main__.py
whitechapel-0.7.dist-info/METADATA
whitechapel-0.7.dist-info/WHEEL
whitechapel-0.7.dist-info/entry_points.txt
whitechapel-0.7.dist-info/RECORD
